<?xml version="1.0" encoding="UTF-8"?>


<Localization xmlns="http://gisClient.pisa.intecs.it/localization">

    <!-- ERGORR UI Manager ** START-->
    <labelFirebugWarning>Firebug Warning</labelFirebugWarning>
    <labelFirebugMessage>Firebug is known to cause performance issues with the ErgoRR UI Application.</labelFirebugMessage>

    <labelControlPanelConfiguration>Configuration</labelControlPanelConfiguration>
    <labelControlPanelAbout>About</labelControlPanelAbout>
    <labelControlPanelLogout>Logout</labelControlPanelLogout>
    <labelControlPanelLogging>Catalogue Log</labelControlPanelLogging>
    <labelControlPanelClient>Catalogue Clients</labelControlPanelClient>
    <labelControlPanelHarvest>Harvest</labelControlPanelHarvest>
    <labelHarvestFromFile>Harvest from Local Disk</labelHarvestFromFile>
    <labelHarvestFromURL>Harvest from URL</labelHarvestFromURL>
    <labelEOClientUser>Earth Observation (EO) Client</labelEOClientUser>
    <labelCatalogueCapabilities>Catalogue Capabilities</labelCatalogueCapabilities>
    <labelCIMClientUser>Cataloguing of ISO Metadata (CIM) Client</labelCIMClientUser>
    <labelConfigurationMisc>Misc</labelConfigurationMisc>
    <labelConfigurationDatabase>Database</labelConfigurationDatabase>
    <labelConfigurationSecurity>Security</labelConfigurationSecurity>
    <!-- ERGORR UI Manager ** END-->
    
    <LogoutMessage>Are you sure you want to quit?</LogoutMessage>
</Localization>
